Leonmaister/__init__.py
Leonmaister-3.6.7.dist-info/METADATA
Leonmaister-3.6.7.dist-info/WHEEL
Leonmaister-3.6.7.dist-info/top_level.txt
Leonmaister-3.6.7.dist-info/RECORD
